mdtraj/__init__.py
mdtraj/_lprmsd.cpython-310-darwin.so
mdtraj/_rmsd.cpython-310-darwin.so
mdtraj/io.py
mdtraj/version.py
mdtraj/core/__init__.py
mdtraj/core/element.py
mdtraj/core/residue_names.py
mdtraj/core/selection.py
mdtraj/core/topology.py
mdtraj/core/trajectory.py
mdtraj/core/lib/center.h
mdtraj/core/lib/libtheobald.a
mdtraj/core/lib/theobald_rmsd.h
mdtraj/formats/__init__.py
mdtraj/formats/amberrst.py
mdtraj/formats/arc.py
mdtraj/formats/binpos.cpython-310-darwin.so
mdtraj/formats/dcd.cpython-310-darwin.so
mdtraj/formats/dtr.cpython-310-darwin.so
mdtraj/formats/gro.py
mdtraj/formats/gsd.py
mdtraj/formats/hdf5.py
mdtraj/formats/hoomdxml.py
mdtraj/formats/lammpstrj.py
mdtraj/formats/lh5.py
mdtraj/formats/mdcrd.py
mdtraj/formats/mol2.py
mdtraj/formats/netcdf.py
mdtraj/formats/openmmxml.py
mdtraj/formats/pdbx.py
mdtraj/formats/prmtop.py
mdtraj/formats/psf.py
mdtraj/formats/registry.py
mdtraj/formats/tng.cpython-310-darwin.so
mdtraj/formats/trr.cpython-310-darwin.so
mdtraj/formats/xtc.cpython-310-darwin.so
mdtraj/formats/xyzfile.py
mdtraj/formats/pdb/__init__.py
mdtraj/formats/pdb/pdbfile.py
mdtraj/formats/pdb/pdbstructure.py
mdtraj/formats/pdb/data/pdbNames.xml
mdtraj/formats/pdb/data/residues.xml
mdtraj/geometry/__init__.py
mdtraj/geometry/_geometry.cpython-310-darwin.so
mdtraj/geometry/alignment.py
mdtraj/geometry/angle.py
mdtraj/geometry/contact.py
mdtraj/geometry/dihedral.py
mdtraj/geometry/distance.py
mdtraj/geometry/drid.cpython-310-darwin.so
mdtraj/geometry/dssp.py
mdtraj/geometry/hbond.py
mdtraj/geometry/internal.py
mdtraj/geometry/neighborlist.cpython-310-darwin.so
mdtraj/geometry/neighbors.cpython-310-darwin.so
mdtraj/geometry/order.py
mdtraj/geometry/rdf.py
mdtraj/geometry/rg.py
mdtraj/geometry/sasa.py
mdtraj/geometry/shape.py
mdtraj/geometry/thermodynamic_properties.py
mdtraj/nmr/__init__.py
mdtraj/nmr/scalar_couplings.py
mdtraj/nmr/shift_wrappers.py
mdtraj/reporters/__init__.py
mdtraj/reporters/basereporter.py
mdtraj/reporters/dcdreporter.py
anagenex_mdtraj-1.9.8.dev0.dist-info/LICENSE
anagenex_mdtraj-1.9.8.dev0.dist-info/METADATA
anagenex_mdtraj-1.9.8.dev0.dist-info/WHEEL
anagenex_mdtraj-1.9.8.dev0.dist-info/entry_points.txt
anagenex_mdtraj-1.9.8.dev0.dist-info/top_level.txt
anagenex_mdtraj-1.9.8.dev0.dist-info/RECORD
