Metadata-Version: 2.1
Name: anagenex-mdtraj
Version: 1.9.8.dev0
Summary: MDTraj: A modern, open library for the analysis of molecular dynamics trajectories
Home-page: http://mdtraj.org
Download-URL: https://github.com/rmcgibbo/mdtraj/releases/latest
Author: Robert McGibbon
Author-email: rmcgibbo@gmail.com
Maintainer: In-Ho Yi
Maintainer-email: in-ho@anagenex.com
License: LGPLv2.1+
Platform: Linux
Platform: Mac OS-X
Platform: Unix
Platform: Windows
Classifier: Development Status :: 5 - Production/Stable
Classifier: Intended Audience :: Science/Research
Classifier: Intended Audience :: Developers
Classifier: License :: OSI Approved :: GNU Lesser General Public License v2 or later (LGPLv2+)
Classifier: Programming Language :: C
Classifier: Programming Language :: Python
Classifier: Programming Language :: Python :: 3
Classifier: Topic :: Scientific/Engineering :: Bio-Informatics
Classifier: Topic :: Scientific/Engineering :: Chemistry
Classifier: Operating System :: Microsoft :: Windows
Classifier: Operating System :: POSIX
Classifier: Operating System :: Unix
Classifier: Operating System :: MacOS
Provides: mdtraj
License-File: LICENSE
Requires-Dist: numpy (>=1.6)
Requires-Dist: scipy
Requires-Dist: astunparse
Requires-Dist: pyparsing
